[{
    "id": 1,
    "username": "gogbourne0",
    "email": "mbloxham0@ox.ac.uk",
    "password": "dR9.dRQ*`/tv"
  }, {
    "id": 2,
    "username": "crelph1",
    "email": "drisdale1@hp.com",
    "password": "rA5|QQ3j&9"
  }, {
    "id": 3,
    "username": "cthomasset2",
    "email": "rcammiemile2@phpbb.com",
    "password": "iR6!k>%f9("
  }, {
    "id": 4,
    "username": "jbermingham3",
    "email": "pgemson3@discuz.net",
    "password": "yY2=A*9I6'mH"
  }, {
    "id": 5,
    "username": "iwordsley4",
    "email": "scorballis4@cnbc.com",
    "password": "kN7#M<08K2.dD\\"
  }]
  